Metadata-Version: 1.1
Name: sipster
Version: 0.0.1
Summary: Pure python tools for SIP testing
Home-page: https://github.com/vodik/sipster
Author: Simon Gomizelj
Author-email: simon@vodik.xyz
License: Apache 2
Platform: UNKNOWN
Classifier: Development Status :: 4 - Beta
Classifier: Framework :: Pytest
Classifier: Intended Audience :: Developers
Classifier: Topic :: Software Development :: Testing
Classifier: Programming Language :: Python
Classifier: Programming Language :: Python :: 3.6
Classifier: Programming Language :: Python :: Implementation :: CPython
Classifier: Operating System :: OS Independent
Classifier: License :: OSI Approved :: Apache Software License
